setup.cfg
setup.py
pydataportability/__init__.py
pydataportability.microformats.base.egg-info/PKG-INFO
pydataportability.microformats.base.egg-info/SOURCES.txt
pydataportability.microformats.base.egg-info/dependency_links.txt
pydataportability.microformats.base.egg-info/entry_points.txt
pydataportability.microformats.base.egg-info/namespace_packages.txt
pydataportability.microformats.base.egg-info/not-zip-safe
pydataportability.microformats.base.egg-info/requires.txt
pydataportability.microformats.base.egg-info/top_level.txt
pydataportability/microformats/__init__.py
pydataportability/microformats/base/__init__.py
pydataportability/microformats/base/interfaces.py
pydataportability/microformats/base/parser.py
pydataportability/microformats/base/htmlparsers/__init__.py
pydataportability/microformats/base/htmlparsers/beautifulsoup.py
pydataportability/microformats/base/htmlparsers/etree.py
