Metadata-Version: 1.0
Name: pydataportability.microformats.base
Version: 0.1dev-r44
Summary: Microformats Parser for Python
Home-page: http://mrtopf.de/blog
Author: Christian Scholz
Author-email: cs@comlounge.net
License: LGPL
Keywords: python microformats hcard hevent xfn rel dataportability
Platform: UNKNOWN
Classifier: Framework :: Plone
Classifier: Framework :: Zope2
Classifier: Framework :: Zope3
Classifier: Programming Language :: Python
Classifier: Topic :: Software Development :: Libraries :: Python Modules
